GIUC.py
GIUC-0.2.0.dist-info/LICENSE
GIUC-0.2.0.dist-info/METADATA
GIUC-0.2.0.dist-info/WHEEL
GIUC-0.2.0.dist-info/top_level.txt
GIUC-0.2.0.dist-info/RECORD
