Metadata-Version: 2.1
Name: GIUC
Version: 0.2.0
Summary: Important mathematical functions' collection
Author: Gautham Nair
Author-email: Gautham Nair <gautham.nair.2005@gmail.com>
License: MIT License
Project-URL: Homepage, https://github.com/gauthamnair2005/GIUC
Keywords: utilities,utility,math,mathematics
Classifier: License :: OSI Approved :: MIT License
Classifier: Programming Language :: Python :: 3
Requires-Python: >=3.5
License-File: LICENSE
Provides-Extra: dev
Requires-Dist: black ; extra == 'dev'
Requires-Dist: bumpver ; extra == 'dev'
Requires-Dist: isort ; extra == 'dev'
Requires-Dist: pip-tools ; extra == 'dev'
Requires-Dist: pytest ; extra == 'dev'
